okahu_handlers/__init.py__
okahu_handlers/langchain/__init__.py
okahu_handlers/langchain/callback.py
okahu_handlers-0.0.10.dist-info/METADATA
okahu_handlers-0.0.10.dist-info/WHEEL
okahu_handlers-0.0.10.dist-info/licenses/LICENSE
okahu_handlers-0.0.10.dist-info/RECORD
